{
  "schema_version": "1.0.0",
  "generated_at": "2026-07-18T10:49:07.745Z",
  "mode": "bluesky_public_api_youtube_atom",
  "score_integration": false,
  "endpoint_count": 10,
  "status_counts": {
    "ok": 9,
    "error": 1
  },
  "platform_counts": {
    "youtube": 9,
    "bluesky": 1
  },
  "sources": [
    {
      "endpoint_id": "by_mfa__youtube__belarusmfa",
      "actor_id": "by_mfa",
      "country": "BY",
      "actor_class": "official_state_source",
      "platform": "youtube",
      "priority": "critical",
      "status": "ok",
      "checked_at": "2026-07-18T10:49:05.671Z",
      "duration_ms": 468,
      "item_count": 15,
      "resolved_identifier": "UC1wREjavwTctQq71LcUfbVQ",
      "feed_url": "https://www.youtube.com/feeds/videos.xml?channel_id=UC1wREjavwTctQq71LcUfbVQ",
      "error": ""
    },
    {
      "endpoint_id": "de_afd_bund__youtube__afdtv",
      "actor_id": "de_afd_bund",
      "country": "DE",
      "actor_class": "party_channel",
      "platform": "youtube",
      "priority": "critical",
      "status": "ok",
      "checked_at": "2026-07-18T10:49:05.703Z",
      "duration_ms": 637,
      "item_count": 15,
      "resolved_identifier": "UCq2rogaxLtQFrYG3X3KYNww",
      "feed_url": "https://www.youtube.com/feeds/videos.xml?channel_id=UCq2rogaxLtQFrYG3X3KYNww",
      "error": ""
    },
    {
      "endpoint_id": "de_bsw_bund__youtube__bswbund",
      "actor_id": "de_bsw_bund",
      "country": "DE",
      "actor_class": "party_channel",
      "platform": "youtube",
      "priority": "critical",
      "status": "ok",
      "checked_at": "2026-07-18T10:49:05.705Z",
      "duration_ms": 553,
      "item_count": 15,
      "resolved_identifier": "UCTCb4Fm41JkTtdwd0CXu4xw",
      "feed_url": "https://www.youtube.com/feeds/videos.xml?channel_id=UCTCb4Fm41JkTtdwd0CXu4xw",
      "error": ""
    },
    {
      "endpoint_id": "de_linke_bund__youtube__dielinke",
      "actor_id": "de_linke_bund",
      "country": "DE",
      "actor_class": "party_channel",
      "platform": "youtube",
      "priority": "critical",
      "status": "ok",
      "checked_at": "2026-07-18T10:49:06.290Z",
      "duration_ms": 401,
      "item_count": 15,
      "resolved_identifier": "UCA95T5bSGxNOAODBdbR2rYQ",
      "feed_url": "https://www.youtube.com/feeds/videos.xml?channel_id=UCA95T5bSGxNOAODBdbR2rYQ",
      "error": ""
    },
    {
      "endpoint_id": "de_heidi_reichinnek__bluesky__heidireichinnek_de",
      "actor_id": "de_heidi_reichinnek",
      "country": "DE",
      "actor_class": "political_actor",
      "platform": "bluesky",
      "priority": "high",
      "status": "error",
      "checked_at": "2026-07-18T10:49:06.408Z",
      "duration_ms": 215,
      "item_count": 0,
      "resolved_identifier": "",
      "feed_url": "",
      "error": "HTTP 400"
    },
    {
      "endpoint_id": "de_auf1__youtube__auf1tv",
      "actor_id": "de_auf1",
      "country": "DE",
      "actor_class": "bridge_media",
      "platform": "youtube",
      "priority": "high",
      "status": "ok",
      "checked_at": "2026-07-18T10:49:06.489Z",
      "duration_ms": 360,
      "item_count": 15,
      "resolved_identifier": "UChkELlk5GBaUCVx8-94IK_Q",
      "feed_url": "https://www.youtube.com/feeds/videos.xml?channel_id=UChkELlk5GBaUCVx8-94IK_Q",
      "error": ""
    },
    {
      "endpoint_id": "de_junge_freiheit__youtube__junge_freiheit",
      "actor_id": "de_junge_freiheit",
      "country": "DE",
      "actor_class": "bridge_media",
      "platform": "youtube",
      "priority": "high",
      "status": "ok",
      "checked_at": "2026-07-18T10:49:06.773Z",
      "duration_ms": 288,
      "item_count": 15,
      "resolved_identifier": "UCXJBRgiZRZvfilIGQ4wN5CQ",
      "feed_url": "https://www.youtube.com/feeds/videos.xml?channel_id=UCXJBRgiZRZvfilIGQ4wN5CQ",
      "error": ""
    },
    {
      "endpoint_id": "de_matthias_helferich__youtube__matthiashelferichmdb",
      "actor_id": "de_matthias_helferich",
      "country": "DE",
      "actor_class": "political_actor",
      "platform": "youtube",
      "priority": "high",
      "status": "ok",
      "checked_at": "2026-07-18T10:49:06.839Z",
      "duration_ms": 500,
      "item_count": 15,
      "resolved_identifier": "UC3Kfx6yNh0e4nFgKadSnYiA",
      "feed_url": "https://www.youtube.com/feeds/videos.xml?channel_id=UC3Kfx6yNh0e4nFgKadSnYiA",
      "error": ""
    },
    {
      "endpoint_id": "de_maximilian_krah__youtube__dr_maximiliankrah5116",
      "actor_id": "de_maximilian_krah",
      "country": "DE",
      "actor_class": "political_actor",
      "platform": "youtube",
      "priority": "high",
      "status": "ok",
      "checked_at": "2026-07-18T10:49:06.999Z",
      "duration_ms": 588,
      "item_count": 15,
      "resolved_identifier": "UCQPvjQbhapgOwprAYusL8Tw",
      "feed_url": "https://www.youtube.com/feeds/videos.xml?channel_id=UCQPvjQbhapgOwprAYusL8Tw",
      "error": ""
    },
    {
      "endpoint_id": "de_tim_kellner__youtube__timkellner",
      "actor_id": "de_tim_kellner",
      "country": "DE",
      "actor_class": "high_reach_political_influencer",
      "platform": "youtube",
      "priority": "high",
      "status": "ok",
      "checked_at": "2026-07-18T10:49:07.211Z",
      "duration_ms": 382,
      "item_count": 15,
      "resolved_identifier": "UCOQFfcGRc886dXP2Oyt5OEg",
      "feed_url": "https://www.youtube.com/feeds/videos.xml?channel_id=UCOQFfcGRc886dXP2Oyt5OEg",
      "error": ""
    }
  ]
}