{
  "schema_version": "1.0.0",
  "generated_at": "2026-07-18T10:18:20.715Z",
  "mode": "website_rss_telegram_metadata",
  "score_integration": false,
  "endpoint_count": 40,
  "status_counts": {
    "ok": 30,
    "error": 9,
    "partial": 1
  },
  "platform_counts": {
    "website": 29,
    "telegram": 11
  },
  "sources": [
    {
      "endpoint_id": "by_mfa__telegram__belarusmfa",
      "actor_id": "by_mfa",
      "country": "BY",
      "actor_class": "official_state_source",
      "platform": "telegram",
      "priority": "critical",
      "status": "ok",
      "checked_at": "2026-07-18T10:17:38.071Z",
      "duration_ms": 864,
      "http_status": 200,
      "final_url": "https://t.me/s/BelarusMFA",
      "discovered_feeds": [],
      "item_count": 10,
      "error": ""
    },
    {
      "endpoint_id": "de_afd_bund__telegram__afdkompakt",
      "actor_id": "de_afd_bund",
      "country": "DE",
      "actor_class": "party_channel",
      "platform": "telegram",
      "priority": "critical",
      "status": "ok",
      "checked_at": "2026-07-18T10:17:38.112Z",
      "duration_ms": 644,
      "http_status": 200,
      "final_url": "https://t.me/s/afdkompakt",
      "discovered_feeds": [],
      "item_count": 10,
      "error": ""
    },
    {
      "endpoint_id": "de_linke_bund__telegram__dielinke",
      "actor_id": "de_linke_bund",
      "country": "DE",
      "actor_class": "party_channel",
      "platform": "telegram",
      "priority": "critical",
      "status": "ok",
      "checked_at": "2026-07-18T10:17:38.113Z",
      "duration_ms": 827,
      "http_status": 200,
      "final_url": "https://t.me/s/dielinke",
      "discovered_feeds": [],
      "item_count": 10,
      "error": ""
    },
    {
      "endpoint_id": "ir_irna__telegram__irna_en",
      "actor_id": "ir_irna",
      "country": "IR",
      "actor_class": "state_media",
      "platform": "telegram",
      "priority": "critical",
      "status": "ok",
      "checked_at": "2026-07-18T10:17:38.906Z",
      "duration_ms": 461,
      "http_status": 200,
      "final_url": "https://t.me/s/Irna_en",
      "discovered_feeds": [],
      "item_count": 10,
      "error": ""
    },
    {
      "endpoint_id": "ru_mfa__telegram__mfarussia",
      "actor_id": "ru_mfa",
      "country": "RU",
      "actor_class": "official_state_source",
      "platform": "telegram",
      "priority": "critical",
      "status": "ok",
      "checked_at": "2026-07-18T10:17:39.085Z",
      "duration_ms": 329,
      "http_status": 200,
      "final_url": "https://t.me/s/MFARussia",
      "discovered_feeds": [],
      "item_count": 5,
      "error": ""
    },
    {
      "endpoint_id": "ru_mod__telegram__mod_russia",
      "actor_id": "ru_mod",
      "country": "RU",
      "actor_class": "official_state_source",
      "platform": "telegram",
      "priority": "critical",
      "status": "ok",
      "checked_at": "2026-07-18T10:17:39.090Z",
      "duration_ms": 630,
      "http_status": 200,
      "final_url": "https://t.me/s/mod_russia",
      "discovered_feeds": [],
      "item_count": 10,
      "error": ""
    },
    {
      "endpoint_id": "ru_mod__telegram__mod_russia_en",
      "actor_id": "ru_mod",
      "country": "RU",
      "actor_class": "official_state_source",
      "platform": "telegram",
      "priority": "critical",
      "status": "ok",
      "checked_at": "2026-07-18T10:17:39.518Z",
      "duration_ms": 398,
      "http_status": 200,
      "final_url": "https://t.me/s/mod_russia_en",
      "discovered_feeds": [],
      "item_count": 10,
      "error": ""
    },
    {
      "endpoint_id": "ru_rt_global__telegram__rtnews",
      "actor_id": "ru_rt_global",
      "country": "RU",
      "actor_class": "state_media",
      "platform": "telegram",
      "priority": "critical",
      "status": "error",
      "checked_at": "2026-07-18T10:17:39.564Z",
      "duration_ms": 556,
      "http_status": 200,
      "final_url": "https://t.me/rtnews",
      "discovered_feeds": [],
      "item_count": 0,
      "error": "No public Telegram messages found"
    },
    {
      "endpoint_id": "ru_rybar__telegram__rybar",
      "actor_id": "ru_rybar",
      "country": "RU",
      "actor_class": "milblogger",
      "platform": "telegram",
      "priority": "critical",
      "status": "ok",
      "checked_at": "2026-07-18T10:17:39.870Z",
      "duration_ms": 494,
      "http_status": 200,
      "final_url": "https://t.me/s/rybar",
      "discovered_feeds": [],
      "item_count": 10,
      "error": ""
    },
    {
      "endpoint_id": "ru_war_on_fakes__telegram__warfakes",
      "actor_id": "ru_war_on_fakes",
      "country": "RU",
      "actor_class": "known_fimi_infrastructure",
      "platform": "telegram",
      "priority": "critical",
      "status": "ok",
      "checked_at": "2026-07-18T10:17:40.067Z",
      "duration_ms": 636,
      "http_status": 200,
      "final_url": "https://t.me/s/warfakes",
      "discovered_feeds": [],
      "item_count": 6,
      "error": ""
    },
    {
      "endpoint_id": "ye_almasirah__telegram__almasirah_en",
      "actor_id": "ye_almasirah",
      "country": "YE",
      "actor_class": "armed_group_media",
      "platform": "telegram",
      "priority": "critical",
      "status": "ok",
      "checked_at": "2026-07-18T10:17:40.269Z",
      "duration_ms": 396,
      "http_status": 200,
      "final_url": "https://t.me/s/Almasirah_En",
      "discovered_feeds": [],
      "item_count": 10,
      "error": ""
    },
    {
      "endpoint_id": "by_belta__website__eng_belta_by",
      "actor_id": "by_belta",
      "country": "BY",
      "actor_class": "state_media",
      "platform": "website",
      "priority": "critical",
      "status": "ok",
      "checked_at": "2026-07-18T10:17:40.515Z",
      "duration_ms": 848,
      "http_status": 200,
      "final_url": "https://eng.belta.by/",
      "discovered_feeds": [],
      "item_count": 1,
      "error": ""
    },
    {
      "endpoint_id": "by_mfa__website__mfa_gov_by_en",
      "actor_id": "by_mfa",
      "country": "BY",
      "actor_class": "official_state_source",
      "platform": "website",
      "priority": "critical",
      "status": "ok",
      "checked_at": "2026-07-18T10:17:40.815Z",
      "duration_ms": 1965,
      "http_status": 200,
      "final_url": "https://mfa.gov.by/en/",
      "discovered_feeds": [],
      "item_count": 1,
      "error": ""
    },
    {
      "endpoint_id": "cn_cgtn__website__cgtn_com",
      "actor_id": "cn_cgtn",
      "country": "CN",
      "actor_class": "state_media",
      "platform": "website",
      "priority": "critical",
      "status": "ok",
      "checked_at": "2026-07-18T10:17:40.852Z",
      "duration_ms": 302,
      "http_status": 200,
      "final_url": "https://www.cgtn.com/",
      "discovered_feeds": [],
      "item_count": 1,
      "error": ""
    },
    {
      "endpoint_id": "cn_embassy_germany__website__de_china_embassy_gov_cn_det",
      "actor_id": "cn_embassy_germany",
      "country": "CN",
      "actor_class": "official_state_source",
      "platform": "website",
      "priority": "critical",
      "status": "ok",
      "checked_at": "2026-07-18T10:17:41.304Z",
      "duration_ms": 1306,
      "http_status": 200,
      "final_url": "https://de.china-embassy.gov.cn/det/",
      "discovered_feeds": [],
      "item_count": 1,
      "error": ""
    },
    {
      "endpoint_id": "cn_mfa__website__mfa_gov_cn_eng",
      "actor_id": "cn_mfa",
      "country": "CN",
      "actor_class": "official_state_source",
      "platform": "website",
      "priority": "critical",
      "status": "ok",
      "checked_at": "2026-07-18T10:17:41.513Z",
      "duration_ms": 1697,
      "http_status": 200,
      "final_url": "https://www.mfa.gov.cn/eng/",
      "discovered_feeds": [],
      "item_count": 1,
      "error": ""
    },
    {
      "endpoint_id": "cn_spamouflage__website__blog_google_threat_analysis_group_over_50000_instances_of_dragonbridge_activity_disrupted_in_2022",
      "actor_id": "cn_spamouflage",
      "country": "CN",
      "actor_class": "known_fimi_infrastructure",
      "platform": "website",
      "priority": "critical",
      "status": "ok",
      "checked_at": "2026-07-18T10:17:42.761Z",
      "duration_ms": 340,
      "http_status": 200,
      "final_url": "https://blog.google/threat-analysis-group/over-50000-instances-of-dragonbridge-activity-disrupted-in-2022/",
      "discovered_feeds": [],
      "item_count": 1,
      "error": ""
    },
    {
      "endpoint_id": "cn_xinhua__website__english_news_cn",
      "actor_id": "cn_xinhua",
      "country": "CN",
      "actor_class": "state_media",
      "platform": "website",
      "priority": "critical",
      "status": "ok",
      "checked_at": "2026-07-18T10:17:42.931Z",
      "duration_ms": 1338,
      "http_status": 200,
      "final_url": "https://english.news.cn/",
      "discovered_feeds": [],
      "item_count": 1,
      "error": ""
    },
    {
      "endpoint_id": "de_afd_bundestag__website__afdbundestag_de",
      "actor_id": "de_afd_bundestag",
      "country": "DE",
      "actor_class": "parliamentary_group",
      "platform": "website",
      "priority": "critical",
      "status": "partial",
      "checked_at": "2026-07-18T10:17:43.251Z",
      "duration_ms": 25069,
      "http_status": 200,
      "final_url": "https://afdbundestag.de/",
      "discovered_feeds": [
        "https://afdbundestag.de/feed/",
        "https://afdbundestag.de/comments/feed/"
      ],
      "item_count": 1,
      "error": "Feed discovery partial: This operation was aborted"
    },
    {
      "endpoint_id": "de_anti_spiegel__website__anti_spiegel_ru",
      "actor_id": "de_anti_spiegel",
      "country": "DE",
      "actor_class": "bridge_media",
      "platform": "website",
      "priority": "critical",
      "status": "error",
      "checked_at": "2026-07-18T10:17:43.361Z",
      "duration_ms": 334,
      "http_status": null,
      "final_url": "",
      "discovered_feeds": [],
      "item_count": 0,
      "error": "HTTP 403"
    },
    {
      "endpoint_id": "de_apollo_news__website__apollo_news_net",
      "actor_id": "de_apollo_news",
      "country": "DE",
      "actor_class": "bridge_media",
      "platform": "website",
      "priority": "critical",
      "status": "ok",
      "checked_at": "2026-07-18T10:17:43.845Z",
      "duration_ms": 1335,
      "http_status": 200,
      "final_url": "https://apollo-news.net/",
      "discovered_feeds": [
        "https://apollo-news.net/feed/",
        "https://apollo-news.net/comments/feed/"
      ],
      "item_count": 10,
      "error": ""
    },
    {
      "endpoint_id": "de_auf1__website__auf1_tv",
      "actor_id": "de_auf1",
      "country": "DE",
      "actor_class": "bridge_media",
      "platform": "website",
      "priority": "critical",
      "status": "ok",
      "checked_at": "2026-07-18T10:17:44.419Z",
      "duration_ms": 1013,
      "http_status": 200,
      "final_url": "https://auf1.tv/",
      "discovered_feeds": [],
      "item_count": 1,
      "error": ""
    },
    {
      "endpoint_id": "de_freie_sachsen__website__freie_sachsen_info",
      "actor_id": "de_freie_sachsen",
      "country": "DE",
      "actor_class": "political_movement_channel",
      "platform": "website",
      "priority": "critical",
      "status": "ok",
      "checked_at": "2026-07-18T10:17:45.330Z",
      "duration_ms": 2028,
      "http_status": 200,
      "final_url": "https://freie-sachsen.info/",
      "discovered_feeds": [
        "https://freie-sachsen.info/feed/",
        "https://freie-sachsen.info/comments/feed/"
      ],
      "item_count": 10,
      "error": ""
    },
    {
      "endpoint_id": "de_julian_reichelt__website__nius_de",
      "actor_id": "de_julian_reichelt",
      "country": "DE",
      "actor_class": "high_reach_political_influencer",
      "platform": "website",
      "priority": "critical",
      "status": "ok",
      "checked_at": "2026-07-18T10:17:45.582Z",
      "duration_ms": 873,
      "http_status": 200,
      "final_url": "https://nius.de/",
      "discovered_feeds": [],
      "item_count": 1,
      "error": ""
    },
    {
      "endpoint_id": "de_junge_freiheit__website__jungefreiheit_de",
      "actor_id": "de_junge_freiheit",
      "country": "DE",
      "actor_class": "bridge_media",
      "platform": "website",
      "priority": "critical",
      "status": "ok",
      "checked_at": "2026-07-18T10:17:46.605Z",
      "duration_ms": 1592,
      "http_status": 200,
      "final_url": "https://jungefreiheit.de/",
      "discovered_feeds": [
        "https://jungefreiheit.de/feed/",
        "https://jungefreiheit.de/comments/feed/"
      ],
      "item_count": 10,
      "error": ""
    },
    {
      "endpoint_id": "de_martin_sellner__website__martin_sellner_at",
      "actor_id": "de_martin_sellner",
      "country": "DE",
      "actor_class": "high_reach_political_influencer",
      "platform": "website",
      "priority": "critical",
      "status": "ok",
      "checked_at": "2026-07-18T10:17:47.507Z",
      "duration_ms": 4682,
      "http_status": 200,
      "final_url": "https://martinsellner.info/",
      "discovered_feeds": [
        "https://martinsellner.info/feed/",
        "https://martinsellner.info/comments/feed/"
      ],
      "item_count": 2,
      "error": ""
    },
    {
      "endpoint_id": "de_nius__website__nius_de",
      "actor_id": "de_nius",
      "country": "DE",
      "actor_class": "bridge_media",
      "platform": "website",
      "priority": "critical",
      "status": "ok",
      "checked_at": "2026-07-18T10:17:48.346Z",
      "duration_ms": 1011,
      "http_status": 200,
      "final_url": "https://nius.de/",
      "discovered_feeds": [],
      "item_count": 1,
      "error": ""
    },
    {
      "endpoint_id": "ir_irna__website__en_irna_ir",
      "actor_id": "ir_irna",
      "country": "IR",
      "actor_class": "state_media",
      "platform": "website",
      "priority": "critical",
      "status": "ok",
      "checked_at": "2026-07-18T10:17:49.506Z",
      "duration_ms": 1102,
      "http_status": 200,
      "final_url": "https://en.irna.ir/",
      "discovered_feeds": [],
      "item_count": 1,
      "error": ""
    },
    {
      "endpoint_id": "ir_mfa__website__en_mfa_ir",
      "actor_id": "ir_mfa",
      "country": "IR",
      "actor_class": "official_state_source",
      "platform": "website",
      "priority": "critical",
      "status": "error",
      "checked_at": "2026-07-18T10:17:50.759Z",
      "duration_ms": 7729,
      "http_status": null,
      "final_url": "",
      "discovered_feeds": [],
      "item_count": 0,
      "error": "fetch failed"
    },
    {
      "endpoint_id": "ir_press_tv__website__presstv_ir",
      "actor_id": "ir_press_tv",
      "country": "IR",
      "actor_class": "state_media",
      "platform": "website",
      "priority": "critical",
      "status": "ok",
      "checked_at": "2026-07-18T10:17:52.339Z",
      "duration_ms": 1751,
      "http_status": 200,
      "final_url": "https://www.presstv.ir/",
      "discovered_feeds": [],
      "item_count": 1,
      "error": ""
    },
    {
      "endpoint_id": "ir_sepah_news__website__sepahnews_ir",
      "actor_id": "ir_sepah_news",
      "country": "IR",
      "actor_class": "military_state_media",
      "platform": "website",
      "priority": "critical",
      "status": "ok",
      "checked_at": "2026-07-18T10:17:54.241Z",
      "duration_ms": 2483,
      "http_status": 200,
      "final_url": "https://sepahnews.ir/",
      "discovered_feeds": [
        "https://sepahnews.ir/fa/rss/allnews"
      ],
      "item_count": 10,
      "error": ""
    },
    {
      "endpoint_id": "ru_baltic_fleet__website__eng_mil_ru_en_structure_forces_navy_associations_structure_forces_type_navy_baltic_htm",
      "actor_id": "ru_baltic_fleet",
      "country": "RU",
      "actor_class": "military_source_family",
      "platform": "website",
      "priority": "critical",
      "status": "error",
      "checked_at": "2026-07-18T10:17:56.873Z",
      "duration_ms": 10203,
      "http_status": null,
      "final_url": "",
      "discovered_feeds": [],
      "item_count": 0,
      "error": "fetch failed"
    },
    {
      "endpoint_id": "ru_doppelgaenger__website__euvsdisinfo_eu_key_narratives_in_pro_kremlin_disinformation_campaign_doppelganger",
      "actor_id": "ru_doppelgaenger",
      "country": "RU",
      "actor_class": "known_fimi_infrastructure",
      "platform": "website",
      "priority": "critical",
      "status": "error",
      "checked_at": "2026-07-18T10:17:58.639Z",
      "duration_ms": 1035,
      "http_status": null,
      "final_url": "",
      "discovered_feeds": [],
      "item_count": 0,
      "error": "HTTP 404"
    },
    {
      "endpoint_id": "ru_embassy_germany__website__germany_mid_ru_de_de",
      "actor_id": "ru_embassy_germany",
      "country": "RU",
      "actor_class": "official_state_source",
      "platform": "website",
      "priority": "critical",
      "status": "error",
      "checked_at": "2026-07-18T10:17:59.824Z",
      "duration_ms": 4195,
      "http_status": null,
      "final_url": "",
      "discovered_feeds": [],
      "item_count": 0,
      "error": "HTTP 404"
    },
    {
      "endpoint_id": "ru_foundation_battle_injustice__website__fondfbr_ru",
      "actor_id": "ru_foundation_battle_injustice",
      "country": "RU",
      "actor_class": "known_fimi_infrastructure",
      "platform": "website",
      "priority": "critical",
      "status": "ok",
      "checked_at": "2026-07-18T10:18:04.169Z",
      "duration_ms": 5174,
      "http_status": 200,
      "final_url": "https://fondfbr.ru/",
      "discovered_feeds": [
        "https://fondfbr.ru/feed/",
        "https://fondfbr.ru/comments/feed/"
      ],
      "item_count": 10,
      "error": ""
    },
    {
      "endpoint_id": "ru_kremlin__website__en_kremlin_ru",
      "actor_id": "ru_kremlin",
      "country": "RU",
      "actor_class": "official_state_source",
      "platform": "website",
      "priority": "critical",
      "status": "error",
      "checked_at": "2026-07-18T10:18:07.225Z",
      "duration_ms": 10342,
      "http_status": null,
      "final_url": "",
      "discovered_feeds": [],
      "item_count": 0,
      "error": "fetch failed"
    },
    {
      "endpoint_id": "ru_matryoshka__website__disinfo_eu_doppelganger_and_matryoshka_two_sides_of_the_same_coin",
      "actor_id": "ru_matryoshka",
      "country": "RU",
      "actor_class": "known_fimi_infrastructure",
      "platform": "website",
      "priority": "critical",
      "status": "error",
      "checked_at": "2026-07-18T10:18:08.471Z",
      "duration_ms": 1675,
      "http_status": null,
      "final_url": "",
      "discovered_feeds": [],
      "item_count": 0,
      "error": "HTTP 404"
    },
    {
      "endpoint_id": "ru_mfa__website__mid_ru_en",
      "actor_id": "ru_mfa",
      "country": "RU",
      "actor_class": "official_state_source",
      "platform": "website",
      "priority": "critical",
      "status": "ok",
      "checked_at": "2026-07-18T10:18:09.493Z",
      "duration_ms": 2917,
      "http_status": 200,
      "final_url": "https://mid.ru/en/",
      "discovered_feeds": [],
      "item_count": 1,
      "error": ""
    },
    {
      "endpoint_id": "ru_mod__website__eng_mil_ru",
      "actor_id": "ru_mod",
      "country": "RU",
      "actor_class": "official_state_source",
      "platform": "website",
      "priority": "critical",
      "status": "error",
      "checked_at": "2026-07-18T10:18:10.297Z",
      "duration_ms": 10267,
      "http_status": null,
      "final_url": "",
      "discovered_feeds": [],
      "item_count": 0,
      "error": "fetch failed"
    },
    {
      "endpoint_id": "ru_newsfront__website__news_front_su",
      "actor_id": "ru_newsfront",
      "country": "RU",
      "actor_class": "known_fimi_infrastructure",
      "platform": "website",
      "priority": "critical",
      "status": "ok",
      "checked_at": "2026-07-18T10:18:12.561Z",
      "duration_ms": 1902,
      "http_status": 200,
      "final_url": "https://news-front.su/",
      "discovered_feeds": [
        "https://news-front.su/feed/",
        "https://news-front.su/comments/feed/"
      ],
      "item_count": 10,
      "error": ""
    }
  ]
}